sync_folders/__init__.py
sync_folders/cleaner.py
sync_folders/main.py
sync_folders/purgelog.py
sync_folders-1.2.1.dist-info/LICENSE
sync_folders-1.2.1.dist-info/METADATA
sync_folders-1.2.1.dist-info/WHEEL
sync_folders-1.2.1.dist-info/top_level.txt
sync_folders-1.2.1.dist-info/RECORD
