Metadata-Version: 2.1
Name: sync-folders
Version: 1.2.1
Summary: Library for synchronization two folders
Home-page: https://github.com/mezgoodle/sync-folders
Author: Maxim Zavalniuk
Author-email: mezgoodle@gmail.com
License: MIT
Download-URL: https://github.com/mezgoodle/sync-folders/archive/v1.2.0.tar.gz
Keywords: folders,files,synchronization,sync-folders
Platform: UNKNOWN
Classifier: Topic :: Software Development :: Build Tools
Classifier: License :: OSI Approved :: MIT License
Classifier: Programming Language :: Python :: 3.6
Classifier: Programming Language :: Python :: 3.7
Classifier: Programming Language :: Python :: 3.8
Classifier: Programming Language :: Python :: 3.9
